collection_json.py
collection_json-0.1.1.dist-info/DESCRIPTION.rst
collection_json-0.1.1.dist-info/RECORD
collection_json-0.1.1.dist-info/METADATA
collection_json-0.1.1.dist-info/WHEEL
collection_json-0.1.1.dist-info/top_level.txt
collection_json-0.1.1.dist-info/metadata.json
