Metadata-Version: 2.0
Name: collection-json
Version: 0.1.1
Summary: Small library to work with Collection+JSON documents.
Home-page: http://pypi.python.org/pypi/collection-json
Author: Ricardo Kirkner
Author-email: ricardo@kirkner.com.ar
License: BSD
Platform: UNKNOWN
Classifier: Programming Language :: Python :: 2
Classifier: Programming Language :: Python :: 3
Classifier: Intended Audience :: Developers
Classifier: License :: OSI Approved :: BSD License
Classifier: Topic :: Software Development :: Libraries
Classifier: Topic :: Utilities
